vonc-0.1.0.dist-info/METADATA
vonc-0.1.0.dist-info/WHEEL
vonc-0.1.0.dist-info/licenses/LICENSE.txt
vonc/__init__.py
vonc/vonc.cpython-312-darwin.so
vonc-0.1.0.dist-info/RECORD
