Metadata-Version: 2.4
Name: vonc
Version: 0.1.0
Classifier: Programming Language :: Python
License-File: LICENSE.txt
Summary: Experimental Python web framework accelerated with Rust
Author: djb
License: MIT
Requires-Python: >=3.7
